{
  "type": "sweety_garden:purple_shamrock_patchs",
  "config": {
    "feature": {
      "feature": {
        "type": "minecraft:simple_block",
        "config": {
          "to_place": {
            "type": "minecraft:weighted_state_provider",
            "entries": [
              {
                "data": {
                  "Name": "minecraft:grass"
                },
                "weight": 20
              },
              {
                "data": {
                  "Name": "minecraft:fern"
                },
                "weight": 20
              },
              {
                "data": {
                  "Name": "sweety_garden:purple_shamrock",
                  "Properties": {
                    "facing": "north",
                    "flower_amount": "1"
                  }
                },
                "weight": 1
              },
              {
                "data": {
                  "Name": "sweety_garden:purple_shamrock",
                  "Properties": {
                    "facing": "east",
                    "flower_amount": "1"
                  }
                },
                "weight": 1
              },
              {
                "data": {
                  "Name": "sweety_garden:purple_shamrock",
                  "Properties": {
                    "facing": "south",
                    "flower_amount": "1"
                  }
                },
                "weight": 2
              },
              {
                "data": {
                  "Name": "sweety_garden:purple_shamrock",
                  "Properties": {
                    "facing": "west",
                    "flower_amount": "1"
                  }
                },
                "weight": 2
              },
              {
                "data": {
                  "Name": "sweety_garden:purple_shamrock",
                  "Properties": {
                    "facing": "north",
                    "flower_amount": "2"
                  }
                },
                "weight": 2
              },
              {
                "data": {
                  "Name": "sweety_garden:purple_shamrock",
                  "Properties": {
                    "facing": "east",
                    "flower_amount": "2"
                  }
                },
                "weight": 2
              },
              {
                "data": {
                  "Name": "sweety_garden:purple_shamrock",
                  "Properties": {
                    "facing": "south",
                    "flower_amount": "2"
                  }
                },
                "weight": 2
              },
              {
                "data": {
                  "Name": "sweety_garden:purple_shamrock",
                  "Properties": {
                    "facing": "west",
                    "flower_amount": "2"
                  }
                },
                "weight": 2
              },
              {
                "data": {
                  "Name": "sweety_garden:purple_shamrock",
                  "Properties": {
                    "facing": "north",
                    "flower_amount": "3"
                  }
                },
                "weight": 3
              },
              {
                "data": {
                  "Name": "sweety_garden:purple_shamrock",
                  "Properties": {
                    "facing": "east",
                    "flower_amount": "3"
                  }
                },
                "weight": 3
              },
              {
                "data": {
                  "Name": "sweety_garden:purple_shamrock",
                  "Properties": {
                    "facing": "south",
                    "flower_amount": "3"
                  }
                },
                "weight": 3
              },
              {
                "data": {
                  "Name": "sweety_garden:purple_shamrock",
                  "Properties": {
                    "facing": "west",
                    "flower_amount": "3"
                  }
                },
                "weight": 3
              },
              {
                "data": {
                  "Name": "sweety_garden:purple_shamrock",
                  "Properties": {
                    "facing": "north",
                    "flower_amount": "4"
                  }
                },
                "weight": 3
              },
              {
                "data": {
                  "Name": "sweety_garden:purple_shamrock",
                  "Properties": {
                    "facing": "east",
                    "flower_amount": "4"
                  }
                },
                "weight": 3
              },
              {
                "data": {
                  "Name": "sweety_garden:purple_shamrock",
                  "Properties": {
                    "facing": "south",
                    "flower_amount": "4"
                  }
                },
                "weight": 3
              },
              {
                "data": {
                  "Name": "sweety_garden:purple_shamrock",
                  "Properties": {
                    "facing": "west",
                    "flower_amount": "4"
                  }
                },
                "weight": 3
              }
            ]
          }
        }
      },
      "placement": [
        {
          "type": "minecraft:block_predicate_filter",
          "predicate": {
            "type": "minecraft:matching_blocks",
            "blocks": "minecraft:air"
          }
        }
      ]
    },
    "tries": 65,
    "xz_spread": 4,
    "y_spread": 2
  }
}