{
  "parent": "minecraft:recipes/root",
  "criteria": {
    "has_snail_goo": {
      "conditions": {
        "items": [
          {
            "items": [
              "spawn:mucus"
            ]
          }
        ]
      },
      "trigger": "minecraft:inventory_changed"
    },
    "has_the_recipe": {
      "conditions": {
        "recipe": "crafttweaker:snail_goo_block"
      },
      "trigger": "minecraft:recipe_unlocked"
    }
  },
  "requirements": [
    [
      "has_snail_goo",
      "has_the_recipe"
    ]
  ],
  "rewards": {
    "recipes": [
      "crafttweaker:snail_goo_block"
    ]
  },
  "sends_telemetry_event": false
}